nonebot_plugin_ipinfo/__init__.py
nonebot_plugin_ipinfo/config.py
nonebot_plugin_ipinfo/py.typed
nonebot_plugin_ipinfo/utils.py
nonebot_plugin_ipinfo-1.0.1.dist-info/WHEEL
nonebot_plugin_ipinfo-1.0.1.dist-info/METADATA
nonebot_plugin_ipinfo-1.0.1.dist-info/RECORD
