Metadata-Version: 2.3
Name: nonebot-plugin-ipinfo
Version: 1.0.1
Summary: NoneBot IP 信息查询插件
Author: lyqgzbl
Author-email: lyqgzbl <122811297+lyqgzbl@users.noreply.github.com>
Requires-Dist: ipinfo>=5.1.0,<6.0.0
Requires-Dist: nonebot2>=2.2.1,<3.0.0
Requires-Dist: nonebot-plugin-argot>=0.2.2
Requires-Dist: ip2location-io>=1.0.0,<2.0.0
Requires-Dist: nonebot-plugin-alconna>=0.57.1,<1.0.0
Requires-Python: >=3.10, <4.0
Project-URL: Documentation, https://github.com/lyqgzbl/nonebot-plugin-ipinfo#readme
Project-URL: Homepage, https://github.com/lyqgzbl/nonebot-plugin-ipinfo
Project-URL: Repository, https://github.com/lyqgzbl/nonebot-plugin-ipinfo
